MANIFEST.in
README.txt
setup.py
TransFabric/__init__.py
TransFabric.egg-info/PKG-INFO
TransFabric.egg-info/SOURCES.txt
TransFabric.egg-info/dependency_links.txt
TransFabric.egg-info/requires.txt
TransFabric.egg-info/top_level.txt